srcpic.py
srcpic-0.0.2.dist-info/LICENSE
srcpic-0.0.2.dist-info/METADATA
srcpic-0.0.2.dist-info/WHEEL
srcpic-0.0.2.dist-info/entry_points.txt
srcpic-0.0.2.dist-info/top_level.txt
srcpic-0.0.2.dist-info/RECORD
