Metadata-Version: 2.1
Name: srcpic
Version: 0.0.2
Summary: A command line tool for creating source code pictures.
Author: Harry Downing
Author-email: harry.downing17@gmail.com
Project-URL: repository, https://github.com/harrydowning/srcpic
Classifier: Programming Language :: Python :: 3
Classifier: License :: OSI Approved :: MIT License
Classifier: Operating System :: OS Independent
Requires-Python: >=3.7
License-File: LICENSE
Requires-Dist: pillow
Requires-Dist: numpy
Requires-Dist: docopt
